<annotation>
	<folder>02-Mar-2020</folder>
	<filename>Balamurugan_00023.jpeg</filename>
	<path>D:\Tensorflow\02-Mar-2020\Balamurugan_00023.jpeg</path>
	<source>
		<database>Unknown</database>
	</source>
	<size>
		<width>720</width>
		<height>896</height>
		<depth>3</depth>
	</size>
	<segmented>0</segmented>
	<object>
		<name>Balamurugan</name>
		<pose>Unspecified</pose>
		<truncated>0</truncated>
		<difficult>0</difficult>
		<bndbox>
			<xmin>274</xmin>
			<ymin>274</ymin>
			<xmax>658</xmax>
			<ymax>775</ymax>
		</bndbox>
	</object>
</annotation>
