<annotation>
	<folder>images</folder>
	<filename>Grouped_Images_1002.jpeg</filename>
	<path>D:\Tensorflow\01_Object_Detection_Training_Data\To_be_Uploaded\data\images\Grouped_Images_1002.jpeg</path>
	<source>
		<database>Unknown</database>
	</source>
	<size>
		<width>1280</width>
		<height>720</height>
		<depth>3</depth>
	</size>
	<segmented>0</segmented>
	<object>
		<name>Balamurugan</name>
		<pose>Unspecified</pose>
		<truncated>0</truncated>
		<difficult>0</difficult>
		<bndbox>
			<xmin>503</xmin>
			<ymin>228</ymin>
			<xmax>675</xmax>
			<ymax>420</ymax>
		</bndbox>
	</object>
	<object>
		<name>Balamurugan</name>
		<pose>Unspecified</pose>
		<truncated>0</truncated>
		<difficult>0</difficult>
		<bndbox>
			<xmin>478</xmin>
			<ymin>124</ymin>
			<xmax>700</xmax>
			<ymax>449</ymax>
		</bndbox>
	</object>
	<object>
		<name>Shamik</name>
		<pose>Unspecified</pose>
		<truncated>0</truncated>
		<difficult>0</difficult>
		<bndbox>
			<xmin>998</xmin>
			<ymin>171</ymin>
			<xmax>1138</xmax>
			<ymax>266</ymax>
		</bndbox>
	</object>
	<object>
		<name>Shamik</name>
		<pose>Unspecified</pose>
		<truncated>0</truncated>
		<difficult>0</difficult>
		<bndbox>
			<xmin>959</xmin>
			<ymin>62</ymin>
			<xmax>1165</xmax>
			<ymax>275</ymax>
		</bndbox>
	</object>
</annotation>
