<annotation>
	<folder>images</folder>
	<filename>Suresh_00057.jpeg</filename>
	<path>D:\Tensorflow\01_Object_Detection_Training_Data\To_be_Uploaded\data\images\Suresh_00057.jpeg</path>
	<source>
		<database>Unknown</database>
	</source>
	<size>
		<width>720</width>
		<height>1280</height>
		<depth>3</depth>
	</size>
	<segmented>0</segmented>
	<object>
		<name>Suresh</name>
		<pose>Unspecified</pose>
		<truncated>0</truncated>
		<difficult>0</difficult>
		<bndbox>
			<xmin>436</xmin>
			<ymin>365</ymin>
			<xmax>536</xmax>
			<ymax>496</ymax>
		</bndbox>
	</object>
	<object>
		<name>Suresh</name>
		<pose>Unspecified</pose>
		<truncated>0</truncated>
		<difficult>0</difficult>
		<bndbox>
			<xmin>412</xmin>
			<ymin>306</ymin>
			<xmax>553</xmax>
			<ymax>515</ymax>
		</bndbox>
	</object>
	<object>
		<name>Suresh</name>
		<pose>Unspecified</pose>
		<truncated>0</truncated>
		<difficult>0</difficult>
		<bndbox>
			<xmin>375</xmin>
			<ymin>247</ymin>
			<xmax>583</xmax>
			<ymax>527</ymax>
		</bndbox>
	</object>
	<object>
		<name>Suresh</name>
		<pose>Unspecified</pose>
		<truncated>0</truncated>
		<difficult>0</difficult>
		<bndbox>
			<xmin>55</xmin>
			<ymin>192</ymin>
			<xmax>708</xmax>
			<ymax>555</ymax>
		</bndbox>
	</object>
</annotation>
